{"E-Signature-1.xml":{"originalDocumentName":"Original-document-1.pdf","originalDocumentSigner":"TONJE BERGUM JAHR","originalDocumentDescription":"formular-valgstyre-753294550656139863.pdf","signatureAttachmentName":"E-Signature-1.xml","originalDigest":"BkNs0ZdBVWMVv8y66x0zuL6HDF0g5JWGu8acyqeakVE="},"E-Signature-2.xml":{"originalDocumentName":"Original-document-1.pdf","originalDocumentSigner":"ØIVIND STRØMSTAD SØRHUSBAKKEN","originalDocumentDescription":"formular-valgstyre-753294550656139863.pdf","signatureAttachmentName":"E-Signature-2.xml","originalDigest":"BkNs0ZdBVWMVv8y66x0zuL6HDF0g5JWGu8acyqeakVE="}}