{
    "localSource": "docs/data-store/pdfs-2023/INNSYN---entityId=3020-nordrefollo-kommune&threadId=valgprotokoll_2023%2C_nordre_follo_kommune&attachment=2023-09-14_232848+-+IN+-+att+3-23075ab36800d137b37157ac36dd6d06.pdf.pdf.layout.txt",
    "url": "http://localhost:25081/file.php?entityId=3020-nordrefollo-kommune&threadId=valgprotokoll_2023%2C_nordre_follo_kommune&attachment=2023-09-14_232848+-+IN+-+att+3-23075ab36800d137b37157ac36dd6d06.pdf",
    "downloadTime": "2023-09-16 08:26:05",
    "pdfMetaData": "Title:           Protokoll Valgstyret 13.09.2023\nAuthor:          Kari Raknes\nCreator:         Microsoft Office Word\nProducer:        Aspose.Words for .NET 23.8.0\nCreationDate:    Wed Sep 13 18:22:00 2023 CEST\nModDate:         Thu Sep 14 08:28:00 2023 CEST\nCustom Metadata: no\nMetadata Stream: yes\nTagged:          yes\nUserProperties:  no\nSuspects:        no\nForm:            none\nJavaScript:      no\nPages:           3\nEncrypted:       no\nPage size:       595.35 x 842 pts (A4)\nPage rot:        0\nFile size:       92118 bytes\nOptimized:       no\nPDF version:     1.7",
    "error": true,
    "errorMessage": "No match for regex.\nRegex ..... : ^([0-9]*\\.[0-9]*\\.[0-9]* [0-9]*:[0-9]*:[0-9]*) \\s* Valgprotokoll for valgstyret \\s* Side [0-9]*$m\nLine ...... : Møteprotokoll\nValgstyret\n\nDato:                     13.09.2023 kl. 19:00\nSted:                     Nordre Follo rådhus, møterom Greverud\nMøtende medlemmer:        Hanne Opdan (AP), Hans Martin Enger (MDG), Oddbjørn Lager Nesje (AP),\n                          Tor Anders Østby (SP), Camilla Edi Hille (V), Elin Skifjell (SV), Dag Andreas\n                          Fedøy (Uavhengig), Anne-Beth Skrede (AP), Cecilie Dahl-Jørgensen Pind\n                          (H), Melissa Kristiansen (H), Bjørn Arne Kløvstad (H), J. Kristian Bjerke (H),\n                          Knut Tønnes Steenersen (FRP)\nMøtende\nvaramedlemmerforfall:    Ingen forfall\nAndre møtte:              Jane Short Aurlien, ass. kommunedirektør\nMøtesekretær:             Kari Raknes\n\nKnut Tønnes Steenersen (FRP) var ikke til stede ved møtestart.\nMøtet talte 12 møtende representanter ved møtestart.\n\n\n SAKSKART                                                                                        Side\n\n Saker til behandling\n\n                         Valgstyrets behandling av møtebok for Fylkestingsvalget 2023 i\n 1323   2201723-41                                                                             2\n                         Nordre Follo kommune\n\n                         Valgstyrets behandling av møtebok for Kommunestyrevalget 2023\n 1423   2201723-42                                                                   2\n                         i Nordre Follo kommune\n\nSki, 13.09.2023\n\nHanne Opdan\nOrdfører\n\nMøteinnkallingen enstemmig godkjent i møtet med 12 representanter.\n\nKnut Tønnes Steenersen (FRP) ankom møtet kl. 19.04. Møtet talte 13 møtende representanter.\n\n\n\n\n                                                  1\n\fSaker til behandling\n\n\n\n1323 Valgstyrets behandling av møtebok for Fylkestingsvalget 2023 i Nordre\nFollo kommune\n\nBehandlet av                                            Møtedato           Saknr\n1 Valgstyret                                            13.09.2023         1323\n\n\nKommunedirektørens innstilling\nMøteboken for Fylkestingsvalget 2023 i Nordre Follo kommune godkjennes.\n\n\n\nValgstyret 13.09.2023:\n\nBehandlingvotering:\nMøteboken for Fylkestingsvalget med vedlegg ble sendt ut i forkant av møtet.\n\nFellesforslag:\nOversikt over organiseringen av forhåndsstemmingen legges ved protokollen.\nKommunedirektørens innstilling med tilleggsforslag enstemmig vedtatt.\n\nValgstyrets vedtak 13.09.2023:\nMøteboken for Fylkestingsvalget 2023 i Nordre Follo kommune godkjennes.\nOversikt over organiseringen av forhåndsstemmingen legges ved protokollen.\n\n\n\n\n                                                 2\n\f1423 Valgstyrets behandling av møtebok for Kommunestyrevalget 2023 i\nNordre Follo kommune\n\nBehandlet av                                           Møtedato          Saknr\n1 Valgstyret                                           13.09.2023        1423\n\n\nKommunedirektørens innstilling\nMøteboken for Kommunestyrevalget 2023 i Nordre Follo kommune godkjennes.\n\n\n\nValgstyret 13.09.2023:\n\nBehandling votering:\nMøteboken for Kommunestyrevalget med vedlegg ble sendt ut i forkant av møtet.\n\nFellesforslag:\nOversikt over organiseringen av forhåndsstemmingen legges ved protokollen.\nKommunedirektørens innstilling med tilleggsforslag enstemmig vedtatt.\n\n\nValgstyrets vedtak 13.09.2023:\nMøteboken for Kommunestyrevalget 2023 i Nordre Follo kommune godkjennes.\nOversikt over organiseringen av forhåndsstemmingen legges ved protokollen.\n\n\n\nMøteprotokollen ble enstemmig godkjent.\n\n\n\nOrdfører Hanne Opdan (AP)     Hans Martin Enger (MDG)        Melissa Kristiansen (H)\n\n\n\nRett utskrift:\n\n\nKari Raknes\nmøtesekretær\n\n\n\n\n                                               3\n\n\n#0 2-valgprotokoll-parser.php(574): regexAssertAndReturnMatch()\n#1 2-valgprotokoll-parser.php(369): parseFile_andWriteToDisk()\n#2 {main}"
}