{
    "localSource": "docs/data-store/pdfs-2023/INNSYN---entityId=2015-hasvik-kommune&threadId=valgprotokoll_2023%2C_hasvik_kommune&attachment=2023-09-15_141748+-+IN+-+att+2-a2a6f2707246de9deeb5625fcdbc2952.pdf.pdf.layout.txt",
    "url": "http://localhost:25081/file.php?entityId=2015-hasvik-kommune&threadId=valgprotokoll_2023%2C_hasvik_kommune&attachment=2023-09-15_141748+-+IN+-+att+2-a2a6f2707246de9deeb5625fcdbc2952.pdf",
    "downloadTime": "2023-09-16 08:26:04",
    "pdfMetaData": "Creator:         Canon iR-ADV C7260  PDF\nProducer:        Adobe PSL 1.2e for Canon\u0000\nCreationDate:    Tue Sep 12 19:41:21 2023 CEST\nCustom Metadata: no\nMetadata Stream: yes\nTagged:          no\nUserProperties:  no\nSuspects:        no\nForm:            none\nJavaScript:      no\nPages:           20\nEncrypted:       no\nPage size:       595.2 x 841.44 pts (A4)\nPage rot:        0\nFile size:       1000153 bytes\nOptimized:       no\nPDF version:     1.4",
    "error": true,
    "errorMessage": "No content. Might contain scanned image."
}