{
    "localSource": "docs/data-store/pdfs/www.sola.kommune.no-_f-p1-i72b3e8d7-d82e-4ea9-a3f7-0a7e40f44c64-valgprotokoll-fylkestingsvalget-2019.pdf.pdf.layout.txt",
    "url": "https://www.sola.kommune.no/_f/p1/i72b3e8d7-d82e-4ea9-a3f7-0a7e40f44c64/valgprotokoll-fylkestingsvalget-2019.pdf",
    "downloadTime": "2019-09-14 12:20:37",
    "municipalNameFromUrl": "Sola",
    "pdfMetaData": "Tagged:         no\nUserProperties: no\nSuspects:       no\nForm:           none\nJavaScript:     no\nPages:          15\nEncrypted:      no\nPage size:      595.2 x 841.92 pts (A4)\nPage rot:       0\nFile size:      6117182 bytes\nOptimized:      no\nPDF version:    1.4",
    "error": true,
    "errorMessage": "No content. Might contain scanned image."
}